greip/__init__.py
greip/greip.py
greip-1.0.1.dist-info/LICENSE
greip-1.0.1.dist-info/METADATA
greip-1.0.1.dist-info/WHEEL
greip-1.0.1.dist-info/top_level.txt
greip-1.0.1.dist-info/RECORD
