Metadata-Version: 2.1
Name: greip
Version: 1.0.1
Summary: Python wrapper for Greip API
Home-page: https://github.com/Greipio/python
Author: Greip
Author-email: Greip <info@greip.io>
License: Apache License
Project-URL: Homepage, https://greip.io
Project-URL: Documentation, https://docs.greip.io
Project-URL: Repository, https://github.com/Greipio/python
Project-URL: Issues, https://github.com/Greipio/python/issues
Keywords: geolocation,geoip,fraud-prevention,profanity-detection,fraud-detection,asn-lookup,bin-lookup
Classifier: Programming Language :: Python :: 3
Classifier: License :: OSI Approved :: Apache Software License
Classifier: Operating System :: OS Independent
Classifier: Natural Language :: English
Requires-Python: >=3.6
License-File: LICENSE
Requires-Dist: requests
Provides-Extra: dev
Requires-Dist: pytest; extra == "dev"
